Workbook

Sheet Read Me
A1: FinTech Digital Payment Processing Platform - Product Backlog & Tech Baseline
A3: How to use this workbook
A4: Backlog | B4: 33 Jira-style user stories with acceptance criteria, architect notes, libraries/tools, priority, points, sprint and dependencies. Import into Jira Free / GitHub Projects or work directly from this sheet.
A5: Cells you edit | B5: Status (dropdown), Story Points and Sprint on the Backlog sheet. Yellow cells are the ones meant to be filled in as you progress; everything on Summary updates automatically.
A6: Libraries | B6: Every dependency with Maven coordinates, purpose, which services use it and the stories it supports. 'Avoid' rows list things you should deliberately NOT use, with reasons.
A7: Per-Service Starters | B7: What to tick on start.spring.io for each service, plus what to add manually. Use this when you generate each module.
A8: Infra & Tools | B8: Everything you install or run locally (all free / open source) with images and suggested ports.
A9: Summary | B9: Story counts, points and % complete by epic, sprint and priority (formulas).
A11: Baseline technology decisions (all free)
A12: Java | B12: 21 (LTS, Eclipse Temurin). Virtual threads are available for a performance talking point.
A13: Build | B13: Maven 3.9.x with the Maven Wrapper; one parent POM, one module per service.
A14: Spring Boot | B14: 4.0.x - use the latest 4.0 patch offered by start.spring.io. Use the same minor version in every service.
A15: Spring Cloud | B15: 2025.1.x (the release train for Boot 4.0). Only used for Gateway and CircuitBreaker.
A16: Data / messaging / auth | B16: PostgreSQL (one database per service), Apache Kafka in KRaft mode, Keycloak, Valkey (or Redis) for rate limiting.
A17: Observability | B17: Micrometer + Prometheus + Grafana, OpenTelemetry + Jaeger, Boot structured logging.
A18: Cost | B18: Nothing here needs a paid subscription. Docker Desktop is free for personal use; Rancher Desktop or Docker Engine are fully free alternatives.
A20: Spring Boot 4 differences to expect (tutorials online are often for Boot 3)
A21: Starters renamed | B21: spring-boot-starter-web is now spring-boot-starter-webmvc; OAuth2 starters are now spring-boot-starter-security-oauth2-*; spring-boot-starter-aop became spring-boot-starter-aspectj.
A22: New required starters | B22: Flyway needs spring-boot-starter-flyway and Kafka needs spring-boot-starter-kafka (the libraries alone are no longer enough). RestClient needs spring-boot-starter-restclient.
A23: Test changes | B23: Each starter has a -test companion. @MockBean/@SpyBean are removed (use @MockitoBean/@MockitoSpyBean). MockMvc in @SpringBootTest needs @AutoConfigureMockMvc.
A24: Jackson 3 | B24: JSON classes moved to the tools.jackson packages (annotations stay in com.fasterxml.jackson.annotation).
A25: If something does not resolve | B25: Names in this workbook come from the official Boot 4.0 migration guide. If a dependency fails to resolve, generate a throw-away project on start.spring.io with the same selections and compare.
A27: Legend
A28: Priority | B28: Must = needed for a credible end-to-end demo. Should = strongly recommended. Could = nice to have.
A29: Status values | B29: Not Started, In Progress, In Review, Blocked, Done.
A30: Story points | B30: Relative sizes (1-13) assuming one developer. Re-estimate after Sprint 1 based on your real pace. Sprint 6 is the heaviest - split it into two if needed.
A31: Scope note | B31: This backlog defines WHAT to build and HOW at design level. The implementation is yours to write.

Sheet Backlog
A1: Story ID | B1: Title | C1: Epic | D1: Service | E1: User Story | F1: Acceptance Criteria | G1: Architect Notes | H1: Libraries / Tools | I1: Priority | J1: Story Points | K1: Sprint | L1: Depends On | M1: Status | N1: Interview Talking Point
A2: PAY-001 | B2: Repo and build skeleton | C2: Epic 0: Foundation | D2: Platform (all) | E2: As a developer, I want a mono-repo with a parent build and one module per service, so that all services build consistently. | F2: 1. Given a fresh clone, when I run one build command, then every module compiles and all tests pass. 2. Java version, plugin versions and dependency management are declared once in the parent POM. 3. common-lib contains only shared DTOs, the error model and correlation-ID utilities - no business logic. 4. Modules: api-gateway, payment-service, fraud-service, ledger-service, notification-service, settlement-service, bank-simulator, common-lib. | G2: Maven multi-module with the Maven Wrapper. Package by feature, not by layer. Keep common-lib tiny - shared code couples services. Generate each service skeleton from start.spring.io using the 'Per-Service Starters' sheet. | H2: JDK 21 (Temurin), Maven 3.9.x + wrapper, Spring Boot 4.0.x parent, Spring Cloud 2025.1.x BOM | I2: Must | J2: 3 | K2: 1 | L2: - | M2: Not Started | N2: Mono-repo vs poly-repo; what belongs in a shared library and what does not.
A3: PAY-002 | B3: Local infrastructure with one command | C3: Epic 0: Foundation | D3: Platform (all) | E3: As a developer, I want Docker Compose to start all backing services, so that I can develop offline at zero cost. | F3: 1. One command starts Postgres, Kafka, a Redis-compatible cache, Keycloak, Mailpit and the observability stack; all containers report healthy. 2. Each service gets its own database and DB user - services never read each other's tables. 3. Data survives a container restart (named volumes). 4. Compose profiles separate 'core' from 'observability' so a laptop is not overloaded. | G3: One Postgres container with one logical database + role per service (saves RAM, still enforces isolation). Kafka single node in KRaft mode (no Zookeeper). Use healthchecks with depends_on condition service_healthy. Keep secrets in a git-ignored .env file and commit .env.example. | H3: Docker Compose; images: postgres, apache/kafka, valkey/valkey, keycloak, mailpit, kafka-ui (see 'Infra & Tools') | I3: Must | J3: 3 | K3: 1 | L3: PAY-001 | M3: Not Started | N3: Database-per-service; why Kafka KRaft; reproducible local environments.
A4: PAY-003 | B4: Standard error and API contract | C4: Epic 0: Foundation | D4: common-lib | E4: As an API consumer, I want a consistent error format and versioned endpoints, so that failures are predictable. | F4: 1. Every error response has a machine-readable code, a human message, a correlation ID and a UTC timestamp. 2. Validation errors list each invalid field with a reason. 3. All endpoints live under /api/v1. 4. An OpenAPI spec is generated for every service. | G4: Use RFC 9457 Problem Details (Spring's ProblemDetail) with extension fields (code, correlationId). One @RestControllerAdvice per service; shared base types in common-lib. | H4: spring-boot-starter-webmvc, spring-boot-starter-validation, springdoc-openapi-starter-webmvc-ui 3.0.x | I4: Must | J4: 2 | K4: 1 | L4: PAY-001 | M4: Not Started | N4: Consistent error handling across microservices; Problem Details standard.
A5: PAY-101 | B5: Create a payment | C5: Epic 1: Payment Service | D5: payment-service | E5: As a merchant, I want to create a payment with amount, currency, customer reference and payment-method token, so that I can charge a customer. | F5: 1. Given a valid request, when submitted, then a payment is created in CREATED and its ID is returned with HTTP 201. 2. Amount must be greater than zero and currency must be in the supported list (for example INR, USD, EUR); violations return 400 with field details. 3. Responses never contain raw payment-method data. 4. Payment IDs are non-sequential (UUID or ULID). | G5: Money = long minor units + ISO-4217 currency code; never float/double. The payment-method token is an opaque string from a fake tokenizer - you never store card numbers. Until PAY-701 lands, take merchantId from a request header; PAY-701 replaces it with a JWT claim. Flyway V1 creates the payments table and indexes. | H5: spring-boot-starter-webmvc, -validation, -data-jpa, postgresql, spring-boot-starter-flyway + flyway-database-postgresql; tests: spring-boot-starter-data-jpa-test, Testcontainers PostgreSQL | I5: Must | J5: 5 | K5: 1 | L5: PAY-002, PAY-003 | M5: Not Started | N5: Why money is stored as integer minor units; why raw card data is never stored.
A6: PAY-102 | B6: Idempotency | C6: Epic 1: Payment Service | D6: payment-service | E6: As a merchant, I want retries with the same idempotency key to never double-charge, so that network retries are safe. | F6: 1. Same Idempotency-Key + same body returns the original response and creates no second payment. 2. Same key + different body returns 422 Idempotency Conflict. 3. Two concurrent requests with the same key result in exactly one payment (proven by a test). 4. Keys expire after a configurable window (default 24 hours). 5. POST endpoints reject requests without the header (400). | G6: Insert-first pattern: INSERT the idempotency record (unique on merchant_id + key) before doing any work; on unique violation load the existing record and compare a hash of the request body. Store response snapshot + status (IN_PROGRESS / COMPLETED). Decide and document what a concurrent duplicate sees while the first is IN_PROGRESS (409, or wait briefly). The DB unique constraint is the source of truth - a Valkey/Redis cache may only be a fast path. | H6: spring-boot-starter-data-jpa, postgresql; tests: Testcontainers PostgreSQL, Awaitility (concurrency test) | I6: Must | J6: 8 | K6: 1 | L6: PAY-101 | M6: Not Started | N6: 'How do you prevent double charges?' - the classic payments interview question.
A7: PAY-103 | B7: Payment state machine | C7: Epic 1: Payment Service | D7: payment-service | E7: As the platform, I want a strict payment lifecycle, so that money movement is always in a valid state. | F7: 1. States: CREATED, PENDING_FRAUD_CHECK, IN_REVIEW, AUTHORIZING, AUTHORIZATION_UNKNOWN, AUTHORIZED, DECLINED, FAILED, CAPTURED, EXPIRED, SETTLED, PARTIALLY_REFUNDED, REFUNDED. 2. Invalid transitions (for example FAILED -> CAPTURED) are rejected with a clear error and change nothing. 3. Every transition is written to an append-only history table with timestamp, actor and reason. 4. Concurrent updates to the same payment are detected (optimistic locking): one wins, the other gets 409. | G7: Enum + explicit transition table (Map<State, Set<State>>) inside the domain class. Deliberately NOT Spring Statemachine: a hand-written table is easier to reason about, test and explain. JPA @Version for optimistic locking. Draw the state diagram in the README (Mermaid). | H7: spring-boot-starter-data-jpa (@Version); JUnit 5 parameterised tests | I7: Must | J7: 8 | K7: 1 | L7: PAY-101 | M7: Not Started | N7: State machines in payments; optimistic vs pessimistic locking.
A8: PAY-104 | B8: Authorize and capture | C8: Epic 1: Payment Service | D8: payment-service | E8: As a merchant, I want to authorize first and capture later, so that I charge only when goods ship. | F8: 1. Authorize calls the bank (through the PAY-202 client) and moves the payment to AUTHORIZED, DECLINED or FAILED. 2. Capture is allowed only from AUTHORIZED and only once; captured amount cannot exceed the authorized amount. 3. An authorization not captured within N days moves to EXPIRED through a scheduled job. 4. The expiry job is safe when two instances run (each payment is processed by only one). | G8: Single full capture only - partial capture is out of scope (write that down as a decision). Expiry job: @Scheduled + row locking (SELECT ... FOR UPDATE SKIP LOCKED) or a Postgres advisory lock - no extra library required. | H8: Spring @Scheduled (built-in), spring-boot-starter-data-jpa | I8: Must | J8: 8 | K8: 2 | L8: PAY-103, PAY-201 | M8: Not Started | N8: Authorization vs capture in card payments; safe scheduled jobs in multi-instance deployments.
A9: PAY-105 | B9: Query payments | C9: Epic 1: Payment Service | D9: payment-service | E9: As a merchant, I want to fetch a payment and list my payments with filters, so that I can track them. | F9: 1. GET by ID returns status, amounts and transition history. 2. The list endpoint supports filters (status, date range) with cursor pagination and stable sorting. 3. A merchant sees only its own payments; other merchants' IDs return 404. | G9: Cursor (keyset) pagination on (created_at, id) instead of OFFSET - stays fast on large tables. Composite index on (merchant_id, status, created_at). Use the merchantId header until PAY-701. | H9: spring-boot-starter-webmvc, spring-boot-starter-data-jpa | I9: Must | J9: 3 | K9: 2 | L9: PAY-101, PAY-103 | M9: Not Started | N9: Keyset vs offset pagination.
A10: PAY-201 | B10: Bank simulator | C10: Epic 2: Bank Simulator & Resilience | D10: bank-simulator | E10: As a developer, I want a fake acquiring bank with configurable behaviour, so that I can test failure modes deterministically and for free. | F10: 1. Endpoints for authorize, capture, refund and status-by-reference mimic a bank. 2. Behaviour is controllable: approve, decline, slow response, timeout, random 5xx - through special amounts and an admin config endpoint. 3. The simulator honours an idempotency reference so repeated calls return the same result. 4. It can produce a daily settlement CSV (consumed by PAY-802). | G10: Separate deployable with in-memory state. Document a 'magic amounts' convention (for example amounts ending in 01 = decline, 02 = timeout, 03 = HTTP 500). Treat it as a real external dependency: payment-service must never import its code. | H10: spring-boot-starter-webmvc, -validation, -actuator | I10: Must | J10: 5 | K10: 2 | L10: PAY-001, PAY-003 | M10: Not Started | N10: How I tested failure scenarios without a paid bank sandbox.
A11: PAY-202 | B11: Resilient bank integration | C11: Epic 2: Bank Simulator & Resilience | D11: payment-service | E11: As the platform, I want bank calls to survive failures, so that one bad dependency does not take us down. | F11: 1. Explicit connect and read timeouts on every bank call. 2. Retries with exponential backoff and jitter, only in safe (idempotent) cases. 3. A circuit breaker opens after a failure-rate threshold and fails fast; a half-open probe recovers. 4. A concurrency limit (bulkhead) caps parallel bank calls. 5. Each behaviour is proven against the simulator or a stubbed server. | G11: Wrap RestClient behind a BankGateway interface (port/adapter). Circuit breaker + bulkhead via Spring Cloud CircuitBreaker (Resilience4j); retry via Spring Framework 7's built-in retry support. Be ready to explain why retrying a non-idempotent call is dangerous and how the bank idempotency reference fixes it. | H11: spring-boot-starter-restclient, spring-cloud-starter-circuitbreaker-resilience4j; tests: WireMock | I11: Must | J11: 8 | K11: 2 | L11: PAY-201, PAY-103 | M11: Not Started | N11: Timeouts, retries, circuit breakers and bulkheads - and how they interact.
A12: PAY-203 | B12: Unknown-outcome handling | C12: Epic 2: Bank Simulator & Resilience | D12: payment-service | E12: As the platform, I want to handle 'the bank timed out - did the charge happen?', so that we neither lose nor double-charge money. | F12: 1. On a bank timeout the payment moves to AUTHORIZATION_UNKNOWN - never straight to FAILED. 2. A recovery job asks the bank for the real status using the idempotency reference and resolves the payment. 3. After N unsuccessful attempts the payment is flagged for manual review and an alert metric increments. 4. No scenario results in a double charge or a lost authorization. | G12: This is the hardest realistic problem in payments. The recovery job uses the same locking approach as PAY-104, with backoff between polls and an attempts table. | H12: Spring @Scheduled; tests: Awaitility + simulator timeout mode | I12: Must | J12: 8 | K12: 2 | L12: PAY-202 | M12: Not Started | N12: Handling the 'unknown' state; why a timeout must not simply be marked failed.
A13: PAY-301 | B13: Transactional outbox | C13: Epic 3: Event-Driven Backbone | D13: payment-service | E13: As the platform, I want state changes and event publishing to be atomic, so that we never save a payment without emitting its event. | F13: 1. The payment update and its outbox row are written in the same DB transaction. 2. A relay publishes outbox rows to Kafka and marks them published; unpublished rows survive restarts. 3. If Kafka is down, events are published after it returns and none are lost. 4. Two relay instances never publish the same row twice (or duplicates are harmless because of PAY-303). | G13: Outbox table: id, aggregate_id, event_type, payload (JSON), created_at, published_at. Relay = scheduled poller using SELECT ... FOR UPDATE SKIP LOCKED in small batches. Producer: acks=all + idempotence enabled. Debezium CDC is a valid free stretch goal - be able to explain it. Delivery is at-least-once, so consumers must be idempotent. | H13: spring-boot-starter-kafka, spring-boot-starter-data-jpa; tests: Testcontainers Kafka; Kafka UI to inspect topics | I13: Must | J13: 8 | K13: 3 | L13: PAY-103, PAY-002 | M13: Not Started | N13: The dual-write problem and the transactional outbox pattern.
... A34: PAY-1005 | B34: Portfolio packaging | C34: Epic 10: Quality, Deployment & Packaging | D34: Platform (all) | E34: As a candidate, I want the repository to be interview-ready, so that reviewers grasp the design in minutes. | F34: 1. README contains: architecture diagram, sequence diagrams (happy path and bank-timeout path), run instructions and a design-decision summary. 2. ADRs in docs/adr cover: outbox vs dual write, choreography vs orchestration, fail-open vs fail-closed, synchronous fraud call, no Spring Statemachine. 3. OpenAPI specs and a Bruno/Postman collection are included. 4. A 2-minute demo script for interviews is written. | G34: GitHub renders Mermaid natively - keep diagrams as code. Use the MADR format for ADRs. Add a 'Known limitations / what I would do next' section; interviewers value honesty. | H34: Mermaid (in Markdown), Bruno or Postman, optional draw.io | I34: Must | J34: 3 | K34: 6 | L34: All | M34: Not Started | N34: Telling the story of the project in 2 minutes.

Sheet Summary
A1: Backlog Summary (formulas - updates as you change Status / Points / Sprint)
A3: By epic
A4: Epic | B4: Stories | C4: Points | D4: Done stories | E4: Done points | F4: % complete (points)
A5: Epic 0: Foundation | B5: =COUNTIF(Backlog!$C$2:$C$34,$A5) -> 3 | C5: =SUMIF(Backlog!$C$2:$C$34,$A5,Backlog!$J$2:$J$34) -> 8 | D5: =COUNTIFS(Backlog!$C$2:$C$34,$A5,Backlog!$M$2:$M$34,"Done") -> 0 | E5: =SUMIFS(Backlog!$J$2:$J$34,Backlog!$C$2:$C$34,$A5,Backlog!$M$2:$M$34,"Done") -> 0 | F5: =IF(C5=0,0,E5/C5) -> 0
A6: Epic 1: Payment Service | B6: =COUNTIF(Backlog!$C$2:$C$34,$A6) -> 5 | C6: =SUMIF(Backlog!$C$2:$C$34,$A6,Backlog!$J$2:$J$34) -> 32 | D6: =COUNTIFS(Backlog!$C$2:$C$34,$A6,Backlog!$M$2:$M$34,"Done") -> 0 | E6: =SUMIFS(Backlog!$J$2:$J$34,Backlog!$C$2:$C$34,$A6,Backlog!$M$2:$M$34,"Done") -> 0 | F6: =IF(C6=0,0,E6/C6) -> 0
A7: Epic 2: Bank Simulator & Resilience | B7: =COUNTIF(Backlog!$C$2:$C$34,$A7) -> 3 | C7: =SUMIF(Backlog!$C$2:$C$34,$A7,Backlog!$J$2:$J$34) -> 21 | D7: =COUNTIFS(Backlog!$C$2:$C$34,$A7,Backlog!$M$2:$M$34,"Done") -> 0 | E7: =SUMIFS(Backlog!$J$2:$J$34,Backlog!$C$2:$C$34,$A7,Backlog!$M$2:$M$34,"Done") -> 0 | F7: =IF(C7=0,0,E7/C7) -> 0
A8: Epic 3: Event-Driven Backbone | B8: =COUNTIF(Backlog!$C$2:$C$34,$A8) -> 3 | C8: =SUMIF(Backlog!$C$2:$C$34,$A8,Backlog!$J$2:$J$34) -> 19 | D8: =COUNTIFS(Backlog!$C$2:$C$34,$A8,Backlog!$M$2:$M$34,"Done") -> 0 | E8: =SUMIFS(Backlog!$J$2:$J$34,Backlog!$C$2:$C$34,$A8,Backlog!$M$2:$M$34,"Done") -> 0 | F8: =IF(C8=0,0,E8/C8) -> 0
A9: Epic 4: Fraud Service | B9: =COUNTIF(Backlog!$C$2:$C$34,$A9) -> 2 | C9: =SUMIF(Backlog!$C$2:$C$34,$A9,Backlog!$J$2:$J$34) -> 10 | D9: =COUNTIFS(Backlog!$C$2:$C$34,$A9,Backlog!$M$2:$M$34,"Done") -> 0 | E9: =SUMIFS(Backlog!$J$2:$J$34,Backlog!$C$2:$C$34,$A9,Backlog!$M$2:$M$34,"Done") -> 0 | F9: =IF(C9=0,0,E9/C9) -> 0
A10: Epic 5: Ledger Service | B10: =COUNTIF(Backlog!$C$2:$C$34,$A10) -> 3 | C10: =SUMIF(Backlog!$C$2:$C$34,$A10,Backlog!$J$2:$J$34) -> 18 | D10: =COUNTIFS(Backlog!$C$2:$C$34,$A10,Backlog!$M$2:$M$34,"Done") -> 0 | E10: =SUMIFS(Backlog!$J$2:$J$34,Backlog!$C$2:$C$34,$A10,Backlog!$M$2:$M$34,"Done") -> 0 | F10: =IF(C10=0,0,E10/C10) -> 0
A11: Epic 6: Notifications & Webhooks | B11: =COUNTIF(Backlog!$C$2:$C$34,$A11) -> 2 | C11: =SUMIF(Backlog!$C$2:$C$34,$A11,Backlog!$J$2:$J$34) -> 11 | D11: =COUNTIFS(Backlog!$C$2:$C$34,$A11,Backlog!$M$2:$M$34,"Done") -> 0 | E11: =SUMIFS(Backlog!$J$2:$J$34,Backlog!$C$2:$C$34,$A11,Backlog!$M$2:$M$34,"Done") -> 0 | F11: =IF(C11=0,0,E11/C11) -> 0
A12: Epic 7: Security | B12: =COUNTIF(Backlog!$C$2:$C$34,$A12) -> 3 | C12: =SUMIF(Backlog!$C$2:$C$34,$A12,Backlog!$J$2:$J$34) -> 16 | D12: =COUNTIFS(Backlog!$C$2:$C$34,$A12,Backlog!$M$2:$M$34,"Done") -> 0 | E12: =SUMIFS(Backlog!$J$2:$J$34,Backlog!$C$2:$C$34,$A12,Backlog!$M$2:$M$34,"Done") -> 0 | F12: =IF(C12=0,0,E12/C12) -> 0
A13: Epic 8: Settlement & Reconciliation | B13: =COUNTIF(Backlog!$C$2:$C$34,$A13) -> 2 | C13: =SUMIF(Backlog!$C$2:$C$34,$A13,Backlog!$J$2:$J$34) -> 16 | D13: =COUNTIFS(Backlog!$C$2:$C$34,$A13,Backlog!$M$2:$M$34,"Done") -> 0 | E13: =SUMIFS(Backlog!$J$2:$J$34,Backlog!$C$2:$C$34,$A13,Backlog!$M$2:$M$34,"Done") -> 0 | F13: =IF(C13=0,0,E13/C13) -> 0
A14: Epic 9: Observability | B14: =COUNTIF(Backlog!$C$2:$C$34,$A14) -> 2 | C14: =SUMIF(Backlog!$C$2:$C$34,$A14,Backlog!$J$2:$J$34) -> 10 | D14: =COUNTIFS(Backlog!$C$2:$C$34,$A14,Backlog!$M$2:$M$34,"Done") -> 0 | E14: =SUMIFS(Backlog!$J$2:$J$34,Backlog!$C$2:$C$34,$A14,Backlog!$M$2:$M$34,"Done") -> 0 | F14: =IF(C14=0,0,E14/C14) -> 0
A15: Epic 10: Quality, Deployment & Packaging | B15: =COUNTIF(Backlog!$C$2:$C$34,$A15) -> 5 | C15: =SUMIF(Backlog!$C$2:$C$34,$A15,Backlog!$J$2:$J$34) -> 25 | D15: =COUNTIFS(Backlog!$C$2:$C$34,$A15,Backlog!$M$2:$M$34,"Done") -> 0 | E15: =SUMIFS(Backlog!$J$2:$J$34,Backlog!$C$2:$C$34,$A15,Backlog!$M$2:$M$34,"Done") -> 0 | F15: =IF(C15=0,0,E15/C15) -> 0
A16: Total | B16: =SUM(B5:B15) -> 33 | C16: =SUM(C5:C15) -> 186 | D16: =SUM(D5:D15) -> 0 | E16: =SUM(E5:E15) -> 0 | F16: =IF(C16=0,0,E16/C16) -> 0
A18: By sprint
A19: Sprint | B19: Stories | C19: Points | D19: Done stories | E19: Done points | F19: % complete (points)
A20: 1 | B20: =COUNTIF(Backlog!$K$2:$K$34,$A20) -> 6 | C20: =SUMIF(Backlog!$K$2:$K$34,$A20,Backlog!$J$2:$J$34) -> 29 | D20: =COUNTIFS(Backlog!$K$2:$K$34,$A20,Backlog!$M$2:$M$34,"Done") -> 0 | E20: =SUMIFS(Backlog!$J$2:$J$34,Backlog!$K$2:$K$34,$A20,Backlog!$M$2:$M$34,"Done") -> 0 | F20: =IF(C20=0,0,E20/C20) -> 0
A21: 2 | B21: =COUNTIF(Backlog!$K$2:$K$34,$A21) -> 5 | C21: =SUMIF(Backlog!$K$2:$K$34,$A21,Backlog!$J$2:$J$34) -> 32 | D21: =COUNTIFS(Backlog!$K$2:$K$34,$A21,Backlog!$M$2:$M$34,"Done") -> 0 | E21: =SUMIFS(Backlog!$J$2:$J$34,Backlog!$K$2:$K$34,$A21,Backlog!$M$2:$M$34,"Done") -> 0 | F21: =IF(C21=0,0,E21/C21) -> 0
A22: 3 | B22: =COUNTIF(Backlog!$K$2:$K$34,$A22) -> 5 | C22: =SUMIF(Backlog!$K$2:$K$34,$A22,Backlog!$J$2:$J$34) -> 29 | D22: =COUNTIFS(Backlog!$K$2:$K$34,$A22,Backlog!$M$2:$M$34,"Done") -> 0 | E22: =SUMIFS(Backlog!$J$2:$J$34,Backlog!$K$2:$K$34,$A22,Backlog!$M$2:$M$34,"Done") -> 0 | F22: =IF(C22=0,0,E22/C22) -> 0
A23: 4 | B23: =COUNTIF(Backlog!$K$2:$K$34,$A23) -> 5 | C23: =SUMIF(Backlog!$K$2:$K$34,$A23,Backlog!$J$2:$J$34) -> 29 | D23: =COUNTIFS(Backlog!$K$2:$K$34,$A23,Backlog!$M$2:$M$34,"Done") -> 0 | E23: =SUMIFS(Backlog!$J$2:$J$34,Backlog!$K$2:$K$34,$A23,Backlog!$M$2:$M$34,"Done") -> 0 | F23: =IF(C23=0,0,E23/C23) -> 0
A24: 5 | B24: =COUNTIF(Backlog!$K$2:$K$34,$A24) -> 5 | C24: =SUMIF(Backlog!$K$2:$K$34,$A24,Backlog!$J$2:$J$34) -> 32 | D24: =COUNTIFS(Backlog!$K$2:$K$34,$A24,Backlog!$M$2:$M$34,"Done") -> 0 | E24: =SUMIFS(Backlog!$J$2:$J$34,Backlog!$K$2:$K$34,$A24,Backlog!$M$2:$M$34,"Done") -> 0 | F24: =IF(C24=0,0,E24/C24) -> 0
A25: 6 | B25: =COUNTIF(Backlog!$K$2:$K$34,$A25) -> 7 | C25: =SUMIF(Backlog!$K$2:$K$34,$A25,Backlog!$J$2:$J$34) -> 35 | D25: =COUNTIFS(Backlog!$K$2:$K$34,$A25,Backlog!$M$2:$M$34,"Done") -> 0 | E25: =SUMIFS(Backlog!$J$2:$J$34,Backlog!$K$2:$K$34,$A25,Backlog!$M$2:$M$34,"Done") -> 0 | F25: =IF(C25=0,0,E25/C25) -> 0
A26: Total | B26: =SUM(B20:B25) -> 33 | C26: =SUM(C20:C25) -> 186 | D26: =SUM(D20:D25) -> 0 | E26: =SUM(E20:E25) -> 0 | F26: =IF(C26=0,0,E26/C26) -> 0
A28: By priority
A29: Priority | B29: Stories | C29: Points | D29: Done stories | E29: Done points | F29: % complete (points)
A30: Must | B30: =COUNTIF(Backlog!$I$2:$I$34,$A30) -> 27 | C30: =SUMIF(Backlog!$I$2:$I$34,$A30,Backlog!$J$2:$J$34) -> 159 | D30: =COUNTIFS(Backlog!$I$2:$I$34,$A30,Backlog!$M$2:$M$34,"Done") -> 0 | E30: =SUMIFS(Backlog!$J$2:$J$34,Backlog!$I$2:$I$34,$A30,Backlog!$M$2:$M$34,"Done") -> 0 | F30: =IF(C30=0,0,E30/C30) -> 0
A31: Should | B31: =COUNTIF(Backlog!$I$2:$I$34,$A31) -> 5 | C31: =SUMIF(Backlog!$I$2:$I$34,$A31,Backlog!$J$2:$J$34) -> 24 | D31: =COUNTIFS(Backlog!$I$2:$I$34,$A31,Backlog!$M$2:$M$34,"Done") -> 0 | E31: =SUMIFS(Backlog!$J$2:$J$34,Backlog!$I$2:$I$34,$A31,Backlog!$M$2:$M$34,"Done") -> 0 | F31: =IF(C31=0,0,E31/C31) -> 0
A32: Could | B32: =COUNTIF(Backlog!$I$2:$I$34,$A32) -> 1 | C32: =SUMIF(Backlog!$I$2:$I$34,$A32,Backlog!$J$2:$J$34) -> 3 | D32: =COUNTIFS(Backlog!$I$2:$I$34,$A32,Backlog!$M$2:$M$34,"Done") -> 0 | E32: =SUMIFS(Backlog!$J$2:$J$34,Backlog!$I$2:$I$34,$A32,Backlog!$M$2:$M$34,"Done") -> 0 | F32: =IF(C32=0,0,E32/C32) -> 0
A34: Note: 'Must' stories alone give a complete end-to-end demo; add 'Should' items as time allows.

Sheet Libraries
A1: # | B1: Category | C1: Library | D1: Maven coordinates (groupId:artifactId) | E1: Purpose | F1: Used in | G1: Related stories | H1: Version guidance | I1: Decision
A2: 1 | B2: Build / BOM | C2: Spring Boot parent | D2: org.springframework.boot:spring-boot-starter-parent | E2: Dependency management, plugin defaults | F2: Parent POM | G2: PAY-001 | H2: Use latest 4.0.x patch | I2: Required
A3: 2 | B3: Build / BOM | C3: Spring Cloud BOM | D3: org.springframework.cloud:spring-cloud-dependencies | E3: Aligned versions for Gateway and CircuitBreaker | F3: Parent POM | G3: PAY-001 | H3: 2025.1.x (the train for Boot 4.0) | I3: Required
A4: 3 | B4: Build | C4: Maven Failsafe plugin | D4: org.apache.maven.plugins:maven-failsafe-plugin | E4: Runs *IT integration tests separately from unit tests | F4: All | G4: PAY-1001 | H4: Managed by Boot parent | I4: Required
A5: 4 | B5: Web | C5: Spring Web MVC | D5: org.springframework.boot:spring-boot-starter-webmvc | E5: REST controllers (servlet stack). Boot 4 name - the old spring-boot-starter-web is deprecated. | F5: payment, fraud, ledger, notification, settlement, bank-simulator | G5: PAY-003, 101, 201 | H5: Managed by Boot - no version | I5: Required
A6: 5 | B6: Web | C6: Validation | D6: org.springframework.boot:spring-boot-starter-validation | E6: Bean Validation for request DTOs | F6: All servlet services | G6: PAY-003, 101 | H6: Managed | I6: Required
A7: 6 | B7: Web | C7: RestClient (outbound HTTP) | D7: org.springframework.boot:spring-boot-starter-restclient | E7: Calls to bank, fraud-service and merchant webhooks; timeouts set explicitly. Boot 4 needs this starter for RestClient auto-configuration. | F7: payment, notification | G7: PAY-202, 402, 601 | H7: Managed | I7: Required
A8: 7 | B8: Web | C8: Actuator | D8: org.springframework.boot:spring-boot-starter-actuator | E8: Health, liveness/readiness probes, metrics endpoint | F8: All | G8: PAY-002, 902, 1004 | H8: Managed | I8: Required
A9: 8 | B9: API docs | C9: springdoc-openapi | D9: org.springdoc:springdoc-openapi-starter-webmvc-ui | E9: OpenAPI spec + Swagger UI | F9: All servlet services | G9: PAY-003, 1005 | H9: NOT managed by Boot - use the 3.0.x line (built for Boot 4) | I9: Required
A10: 9 | B10: Persistence | C10: Spring Data JPA (Hibernate) | D10: org.springframework.boot:spring-boot-starter-data-jpa | E10: Persistence and @Version optimistic locking | F10: payment, fraud, ledger, notification, settlement | G10: PAY-101, 102, 103, 401, 501, 801 | H10: Managed | I10: Required
A11: 10 | B11: Persistence | C11: PostgreSQL JDBC driver | D11: org.postgresql:postgresql | E11: JDBC driver | F11: Same as above | G11: PAY-101 | H11: Managed | I11: Required
A12: 11 | B12: Persistence | C12: Flyway starter | D12: org.springframework.boot:spring-boot-starter-flyway | E12: Schema migrations. Boot 4 requires this starter - flyway-core alone is no longer enough. | F12: Same as above | G12: PAY-101 | H12: Managed | I12: Required
A13: 12 | B13: Persistence | C13: Flyway PostgreSQL module | D13: org.flywaydb:flyway-database-postgresql | E13: Database-specific support needed by recent Flyway versions | F13: Same as above | G13: PAY-101 | H13: Managed by Boot | I13: Required
... A53: 52 | B53: Avoid | C53: Old Boot 3 starter names | D53: spring-boot-starter-web, spring-boot-starter-aop, spring-boot-starter-oauth2-* | E53: Deprecated or renamed in Boot 4 - use the names in this sheet | F53: - | G53: - | H53: - | I53: Avoid
C55: Decision key: Required = install it; Optional = add only if you want the stretch; Built-in = no dependency needed; Avoid = deliberately not used (reason given).

Sheet Per-Service Starters
A1: Service | B1: Suggested port | C1: Tick on start.spring.io (Maven, Java 21, Boot 4.0.x) | D1: Add manually to the POM | E1: Notes
A2: api-gateway | B2: 8080 | C2: Reactive Gateway (Spring Cloud Routing - pick the WebFlux one); OAuth2 Resource Server; Spring Data Reactive Redis; Spring Boot Actuator; Prometheus; OpenTelemetry | D2: - | E2: Keycloak issuer URI and Redis host via environment variables
A3: payment-service | B3: 8081 | C3: Spring Web; Validation; Spring Data JPA; PostgreSQL Driver; Flyway Migration; Spring for Apache Kafka; OAuth2 Resource Server; OAuth2 Client; Resilience4J; Spring Boot Actuator; Prometheus; OpenTelemetry; Testcontainers | D3: spring-boot-starter-restclient; org.flywaydb:flyway-database-postgresql; springdoc-openapi-starter-webmvc-ui (3.0.x); test: testcontainers-postgresql, testcontainers-kafka, wiremock-standalone | E3: Owns payment state, idempotency, outbox. Talks to fraud-service and bank-simulator.
A4: fraud-service | B4: 8082 | C4: Spring Web; Validation; Spring Data JPA; PostgreSQL Driver; Flyway Migration; OAuth2 Resource Server; Spring Boot Actuator; Prometheus; OpenTelemetry; Testcontainers | D4: org.flywaydb:flyway-database-postgresql; springdoc-openapi-starter-webmvc-ui; optional: Spring Data Redis (Access+Driver) for velocity counters | E4: Synchronous risk API - no Kafka needed unless you add audit events.
A5: ledger-service | B5: 8083 | C5: Spring Web; Validation; Spring Data JPA; PostgreSQL Driver; Flyway Migration; Spring for Apache Kafka; OAuth2 Resource Server; Spring Boot Actuator; Prometheus; OpenTelemetry; Testcontainers | D5: org.flywaydb:flyway-database-postgresql; springdoc-openapi-starter-webmvc-ui; test: testcontainers-postgresql, testcontainers-kafka | E5: Consumes payment events; balance and journal queries.
A6: notification-service | B6: 8084 | C6: Spring Web; Validation; Spring Data JPA; PostgreSQL Driver; Flyway Migration; Spring for Apache Kafka; Java Mail Sender; Thymeleaf; OAuth2 Resource Server; Spring Boot Actuator; Prometheus; OpenTelemetry; Testcontainers | D6: spring-boot-starter-restclient; org.flywaydb:flyway-database-postgresql; springdoc-openapi-starter-webmvc-ui; test: wiremock-standalone | E6: Webhooks (RestClient) + email (Mailpit).
A7: settlement-service | B7: 8085 | C7: Spring Web; Validation; Spring Data JPA; PostgreSQL Driver; Flyway Migration; Spring for Apache Kafka; OAuth2 Resource Server; Spring Boot Actuator; Prometheus; OpenTelemetry; Testcontainers | D7: org.apache.commons:commons-csv; org.flywaydb:flyway-database-postgresql; springdoc-openapi-starter-webmvc-ui; optional: Spring Batch (JDBC) | E7: Read model from events, daily batch, reconciliation.
A8: bank-simulator | B8: 8086 | C8: Spring Web; Validation; Spring Boot Actuator | D8: optional: springdoc-openapi-starter-webmvc-ui | E8: No database, no auth: it plays an external bank. In-memory state only.
A9: common-lib | B9: - | C9: None - plain Java 21 module | D9: Only what shared DTOs need (for example jackson-annotations); no Spring starters | E9: Error model, event records, correlation-ID constants. Keep tiny.
A11: Group ID suggestion: com.<yourname>.payments. Package by feature inside each service.
A12: Every service also gets: Testcontainers modules and Awaitility as test-scope dependencies where it uses Postgres/Kafka.
A13: If start.spring.io names differ slightly (Initializr labels change), match by purpose - the Libraries sheet lists the exact Maven coordinates.

Sheet Infra & Tools
A1: Tool | B1: Purpose | C1: Free option / notes | D1: Image or where to get it | E1: Suggested host port | F1: Needed from sprint | G1: Required?
A2: JDK 21 | B2: Compile and run Java | C2: Eclipse Temurin 21 (free OpenJDK build) | D2: adoptium.net, or SDKMAN | E2: - | F2: 1 | G2: Required
A3: Maven 3.9.x | B3: Build tool | C3: Free. Each module ships the Maven Wrapper (mvnw), so a global install is optional | D3: maven.apache.org | E3: - | F3: 1 | G3: Required
A4: IDE | B4: Write and debug code | C4: IntelliJ IDEA (free tier) or VS Code with the Extension Pack for Java | D4: jetbrains.com / code.visualstudio.com | E4: - | F4: 1 | G4: Required
A5: Git + GitHub | B5: Source control, CI, portfolio | C5: Free account. Public repo = free Actions minutes and visible to recruiters | D5: github.com | E5: - | F5: 1 | G5: Required
A6: Docker | B6: Run all backing services | C6: Docker Desktop (free for personal use) or Rancher Desktop / Colima / Docker Engine on Linux | D6: docker.com / rancherdesktop.io | E6: - | F6: 1 | G6: Required
A7: PostgreSQL | B7: Database per service | C7: Official image | D7: postgres (17 or newer) | E7: 5432 | F7: 1 | G7: Required
A8: Apache Kafka | B8: Event backbone (KRaft mode, no Zookeeper) | C8: Official image | D8: apache/kafka | E8: 9092 | F8: 3 | G8: Required
A9: Kafka UI | B9: Inspect topics, consumer lag, DLQ | C9: Open-source, maintained fork | D9: ghcr.io/kafbat/kafka-ui | E9: 8090 | F9: 3 | G9: Recommended
A10: Keycloak | B10: OAuth2 / OIDC identity provider | C10: Open source | D10: quay.io/keycloak/keycloak (26.x) | E10: 8180 | F10: 5 | G10: Required
A11: Valkey (or Redis) | B11: Gateway rate-limit store; optional idempotency cache | C11: Valkey is fully open source and Redis-compatible; Spring's Redis support works with it | D11: valkey/valkey (or redis) | E11: 6379 | F11: 5 | G11: Required
A12: Mailpit | B12: Local SMTP catcher with web UI (replaces the unmaintained MailHog) | C12: Open source | D12: axllent/mailpit | E12: 8025 UI / 1025 SMTP | F12: 4 | G12: Required
A13: Prometheus | B13: Metrics storage and scraping | C13: Open source | D13: prom/prometheus | E13: 9090 | F13: 6 | G13: Required
A14: Grafana | B14: Dashboards and alerts | C14: Open-source edition | D14: grafana/grafana | E14: 3000 | F14: 6 | G14: Required
A15: Jaeger | B15: Distributed trace viewer (OTLP receiver built in) | C15: Open source. Use the v2 image - the old v1 all-in-one image is end-of-life | D15: jaegertracing/jaeger | E15: 16686 UI / 4317-4318 OTLP | F15: 6 | G15: Required
A16: Loki | B16: Log aggregation (stretch) | C16: Open source | D16: grafana/loki | E16: 3100 | F16: 6 | G16: Optional
A17: k6 | B17: Load testing | C17: Open source | D17: grafana/k6 | E17: - | F17: 6 | G17: Required
A18: Kind + kubectl | B18: Local Kubernetes cluster | C18: Free. Minikube is an alternative | D18: kind.sigs.k8s.io / kubernetes.io | E18: - | F18: 6 | G18: Required
A19: API client | B19: Manual API testing | C19: Bruno (open source) or Postman free tier or the IntelliJ HTTP client | D19: usebruno.com / postman.com | E19: - | F19: 1 | G19: Required (pick one)
A20: DBeaver Community | B20: Browse Postgres tables | C20: Free community edition | D20: dbeaver.io | E20: - | F20: 1 | G20: Optional
A21: GitHub Actions | B21: CI pipeline | C21: Free for public repos; monthly free minutes for private repos | D21: github.com/features/actions | E21: - | F21: 6 | G21: Required
A22: Dependabot | B22: Dependency vulnerability alerts | C22: Free on GitHub | D22: github.com | E22: - | F22: 6 | G22: Recommended
A23: Mermaid / draw.io | B23: Diagrams in the README | C23: Free. GitHub renders Mermaid natively | D23: mermaid.js.org / diagrams.net | E23: - | F23: 6 | G23: Required (one)
A25: Laptop sizing: 16 GB RAM is comfortable. Start the 'core' Compose profile daily and the 'observability' profile only when working on Epic 9.
A26: Service ports: api-gateway 8080, payment 8081, fraud 8082, ledger 8083, notification 8084, settlement 8085, bank-simulator 8086 (see Per-Service Starters).
A27: Image tags: pin a specific version tag in Compose instead of 'latest' so the environment stays reproducible.
